[{"year":1950,"catch":161709},{"year":1951,"catch":174520},{"year":1952,"catch":185855},{"year":1953,"catch":226491},{"year":1954,"catch":221582},{"year":1955,"catch":207064},{"year":1956,"catch":196778},{"year":1957,"catch":197795},{"year":1958,"catch":214720},{"year":1959,"catch":198305},{"year":1960,"catch":203346},{"year":1961,"catch":239705},{"year":1962,"catch":200712},{"year":1963,"catch":243754},{"year":1964,"catch":254445},{"year":1965,"catch":242982},{"year":1966,"catch":233170},{"year":1967,"catch":215862},{"year":1968,"catch":212194},{"year":1969,"catch":235389},{"year":1970,"catch":264938},{"year":1971,"catch":223862},{"year":1972,"catch":263380},{"year":1973,"catch":260065},{"year":1974,"catch":258989},{"year":1975,"catch":281320},{"year":1976,"catch":274527},{"year":1977,"catch":292240},{"year":1978,"catch":292941},{"year":1979,"catch":246216},{"year":1980,"catch":279238},{"year":1981,"catch":290218},{"year":1982,"catch":292623},{"year":1983,"catch":357078},{"year":1984,"catch":352928},{"year":1985,"catch":428748},{"year":1986,"catch":529583},{"year":1987,"catch":531142},{"year":1988,"catch":620396},{"year":1989,"catch":456953},{"year":1990,"catch":503220},{"year":1991,"catch":446841},{"year":1992,"catch":479501},{"year":1993,"catch":477103},{"year":1994,"catch":501746},{"year":1995,"catch":515849},{"year":1996,"catch":572859.2},{"year":1997,"catch":590985.2},{"year":1998,"catch":494039},{"year":1999,"catch":501711.5},{"year":2000,"catch":492978},{"year":2001,"catch":480842.6},{"year":2002,"catch":573958.3},{"year":2003,"catch":557439.8},{"year":2004,"catch":592766.5},{"year":2005,"catch":599917.4},{"year":2006,"catch":523465.4},{"year":2007,"catch":516536},{"year":2008,"catch":466126},{"year":2009,"catch":470245},{"year":2010,"catch":468388},{"year":2011,"catch":474432},{"year":2012,"catch":540667},{"year":2013,"catch":576612},{"year":2014,"catch":703175},{"year":2015,"catch":636171},{"year":2016,"catch":642131},{"year":2017,"catch":637615}]
