[{"year":1950,"catch":41692},{"year":1951,"catch":43602},{"year":1952,"catch":38326},{"year":1953,"catch":48583},{"year":1954,"catch":57193},{"year":1955,"catch":52827},{"year":1956,"catch":54582},{"year":1957,"catch":54888},{"year":1958,"catch":73609},{"year":1959,"catch":61166},{"year":1960,"catch":69884},{"year":1961,"catch":55754},{"year":1962,"catch":67029},{"year":1963,"catch":83999},{"year":1964,"catch":82697},{"year":1965,"catch":73781},{"year":1966,"catch":98045},{"year":1967,"catch":94465},{"year":1968,"catch":120104},{"year":1969,"catch":106293},{"year":1970,"catch":125592},{"year":1971,"catch":139283},{"year":1972,"catch":154159},{"year":1973,"catch":145883},{"year":1974,"catch":212369},{"year":1975,"catch":173517},{"year":1976,"catch":175498},{"year":1977,"catch":173714},{"year":1978,"catch":189721},{"year":1979,"catch":183118},{"year":1980,"catch":170091},{"year":1981,"catch":182928},{"year":1982,"catch":264202},{"year":1983,"catch":308700},{"year":1984,"catch":256490},{"year":1985,"catch":268990},{"year":1986,"catch":327419},{"year":1987,"catch":343071},{"year":1988,"catch":341398},{"year":1989,"catch":325099},{"year":1990,"catch":386275},{"year":1991,"catch":347179},{"year":1992,"catch":341078},{"year":1993,"catch":322756},{"year":1994,"catch":345275},{"year":1995,"catch":358924},{"year":1996,"catch":373499},{"year":1997,"catch":365493},{"year":1998,"catch":370835},{"year":1999,"catch":398449},{"year":2000,"catch":443718},{"year":2001,"catch":422261},{"year":2002,"catch":398731},{"year":2003,"catch":427884},{"year":2004,"catch":512648},{"year":2005,"catch":710595},{"year":2006,"catch":833008},{"year":2007,"catch":666570},{"year":2008,"catch":818114},{"year":2009,"catch":561328},{"year":2010,"catch":590853},{"year":2011,"catch":588463},{"year":2012,"catch":605537},{"year":2013,"catch":687250},{"year":2014,"catch":939568},{"year":2015,"catch":1007378},{"year":2016,"catch":635336},{"year":2017,"catch":637547}]
