[{"year":1950,"catch":150100},{"year":1951,"catch":150100},{"year":1952,"catch":150100},{"year":1953,"catch":158600},{"year":1954,"catch":113900},{"year":1955,"catch":113900},{"year":1956,"catch":121100},{"year":1957,"catch":105600},{"year":1958,"catch":47900},{"year":1959,"catch":100300},{"year":1960,"catch":118400},{"year":1961,"catch":207300},{"year":1962,"catch":127100},{"year":1963,"catch":155600},{"year":1964,"catch":212200},{"year":1965,"catch":114600},{"year":1966,"catch":110500},{"year":1967,"catch":86200},{"year":1968,"catch":111300},{"year":1969,"catch":117500},{"year":1970,"catch":166200},{"year":1971,"catch":173100},{"year":1972,"catch":216800},{"year":1973,"catch":144800},{"year":1974,"catch":197739},{"year":1975,"catch":220408},{"year":1976,"catch":295747},{"year":1977,"catch":290833},{"year":1978,"catch":178759},{"year":1979,"catch":158460},{"year":1980,"catch":127483},{"year":1981,"catch":123380},{"year":1982,"catch":115043},{"year":1983,"catch":59209},{"year":1984,"catch":75932},{"year":1985,"catch":82119},{"year":1986,"catch":99342},{"year":1987,"catch":113639},{"year":1988,"catch":124805},{"year":1989,"catch":129758},{"year":1990,"catch":149607},{"year":1991,"catch":155586},{"year":1992,"catch":123141},{"year":1993,"catch":158320},{"year":1994,"catch":177815},{"year":1995,"catch":202537},{"year":1996,"catch":213363},{"year":1997,"catch":249356},{"year":1998,"catch":293271},{"year":1999,"catch":214269},{"year":2000,"catch":223456},{"year":2001,"catch":214592},{"year":2002,"catch":213933},{"year":2003,"catch":234859},{"year":2004,"catch":228621},{"year":2005,"catch":188949},{"year":2006,"catch":166597},{"year":2007,"catch":192224},{"year":2008,"catch":229885},{"year":2009,"catch":182403},{"year":2010,"catch":158031},{"year":2011,"catch":128778},{"year":2012,"catch":138837},{"year":2013,"catch":107090},{"year":2014,"catch":88730},{"year":2015,"catch":56757},{"year":2016,"catch":47393},{"year":2017,"catch":47539},{"year":2018,"catch":57090}]
