[{"year":1950,"catch":16300},{"year":1951,"catch":16300},{"year":1952,"catch":17300},{"year":1953,"catch":20100},{"year":1954,"catch":22000},{"year":1955,"catch":25000},{"year":1956,"catch":27000},{"year":1957,"catch":31100},{"year":1958,"catch":33000},{"year":1959,"catch":30500},{"year":1960,"catch":32700},{"year":1961,"catch":32400},{"year":1962,"catch":33100},{"year":1963,"catch":41200},{"year":1964,"catch":46700},{"year":1965,"catch":45000},{"year":1966,"catch":47700},{"year":1967,"catch":53700},{"year":1968,"catch":48300},{"year":1969,"catch":54500},{"year":1970,"catch":60087},{"year":1971,"catch":65475},{"year":1972,"catch":72060},{"year":1973,"catch":80358},{"year":1974,"catch":84134},{"year":1975,"catch":88022},{"year":1976,"catch":82239},{"year":1977,"catch":84981},{"year":1978,"catch":87029},{"year":1979,"catch":98290},{"year":1980,"catch":113796},{"year":1981,"catch":121102},{"year":1982,"catch":111064},{"year":1983,"catch":123322},{"year":1984,"catch":122510},{"year":1985,"catch":127132},{"year":1986,"catch":121400},{"year":1987,"catch":134178},{"year":1988,"catch":139767},{"year":1989,"catch":156486},{"year":1990,"catch":121987},{"year":1991,"catch":128096},{"year":1992,"catch":148898},{"year":1993,"catch":135597},{"year":1994,"catch":146013},{"year":1995,"catch":142096},{"year":1996,"catch":144538},{"year":1997,"catch":180130},{"year":1998,"catch":174731},{"year":1999,"catch":185030},{"year":2000,"catch":163950},{"year":2001,"catch":181980},{"year":2002,"catch":182384},{"year":2003,"catch":191644},{"year":2004,"catch":187157},{"year":2005,"catch":174521},{"year":2006,"catch":197123},{"year":2007,"catch":191350},{"year":2008,"catch":230388},{"year":2009,"catch":249543},{"year":2010,"catch":248911},{"year":2011,"catch":258447},{"year":2012,"catch":275623},{"year":2013,"catch":385037},{"year":2014,"catch":324894},{"year":2015,"catch":302130},{"year":2016,"catch":293708},{"year":2017,"catch":411402},{"year":2018,"catch":369386.53}]
