[{"year":1950,"catch":14498},{"year":1951,"catch":19402},{"year":1952,"catch":26812},{"year":1953,"catch":24793},{"year":1954,"catch":17416},{"year":1955,"catch":16798},{"year":1956,"catch":21081},{"year":1957,"catch":24331},{"year":1958,"catch":29768},{"year":1959,"catch":23615},{"year":1960,"catch":21772},{"year":1961,"catch":26092},{"year":1962,"catch":28391},{"year":1963,"catch":33748},{"year":1964,"catch":21575},{"year":1965,"catch":21274},{"year":1966,"catch":18026},{"year":1967,"catch":20029},{"year":1968,"catch":17622},{"year":1969,"catch":15637},{"year":1970,"catch":13900},{"year":1971,"catch":14800},{"year":1972,"catch":18200},{"year":1973,"catch":19300},{"year":1974,"catch":19891},{"year":1975,"catch":19218},{"year":1976,"catch":17915},{"year":1977,"catch":17004},{"year":1978,"catch":15695},{"year":1979,"catch":17633},{"year":1980,"catch":12862},{"year":1981,"catch":12545},{"year":1982,"catch":13268},{"year":1983,"catch":17790},{"year":1984,"catch":14023},{"year":1985,"catch":14122},{"year":1986,"catch":16860},{"year":1987,"catch":17333},{"year":1988,"catch":18947},{"year":1989,"catch":17053},{"year":1990,"catch":17736},{"year":1991,"catch":21212},{"year":1992,"catch":19285},{"year":1993,"catch":15406},{"year":1994,"catch":14785},{"year":1995,"catch":14408},{"year":1996,"catch":16843},{"year":1997,"catch":13004},{"year":1998,"catch":14078},{"year":1999,"catch":16030},{"year":2000,"catch":17990},{"year":2001,"catch":20344},{"year":2002,"catch":16328},{"year":2003,"catch":18259},{"year":2004,"catch":14831},{"year":2005,"catch":16643},{"year":2006,"catch":17965},{"year":2007,"catch":17783},{"year":2008,"catch":15937},{"year":2009,"catch":17465},{"year":2010,"catch":15052},{"year":2011,"catch":13536},{"year":2012,"catch":12469},{"year":2013,"catch":11153},{"year":2014,"catch":9636},{"year":2015,"catch":11092},{"year":2016,"catch":11735},{"year":2017,"catch":11033},{"year":2018,"catch":14262}]
