[{"year":1950,"catch":20400},{"year":1951,"catch":21500},{"year":1952,"catch":25900},{"year":1953,"catch":33100},{"year":1954,"catch":35100},{"year":1955,"catch":40600},{"year":1956,"catch":47200},{"year":1957,"catch":45000},{"year":1958,"catch":58400},{"year":1959,"catch":58200},{"year":1960,"catch":53200},{"year":1961,"catch":65900},{"year":1962,"catch":59200},{"year":1963,"catch":66700},{"year":1964,"catch":49700},{"year":1965,"catch":72400},{"year":1966,"catch":88800},{"year":1967,"catch":59902},{"year":1968,"catch":70053},{"year":1969,"catch":72312},{"year":1970,"catch":53162},{"year":1971,"catch":61392},{"year":1972,"catch":67925},{"year":1973,"catch":106668},{"year":1974,"catch":99314},{"year":1975,"catch":85260},{"year":1976,"catch":65603},{"year":1977,"catch":64942},{"year":1978,"catch":65709},{"year":1979,"catch":89563},{"year":1980,"catch":87269},{"year":1981,"catch":86156},{"year":1982,"catch":70690.8},{"year":1983,"catch":52102},{"year":1984,"catch":39074.6},{"year":1985,"catch":41833.2},{"year":1986,"catch":74002.04},{"year":1987,"catch":92637},{"year":1988,"catch":79218},{"year":1989,"catch":61321.8},{"year":1990,"catch":51824},{"year":1991,"catch":52458},{"year":1992,"catch":62520},{"year":1993,"catch":67749},{"year":1994,"catch":89581},{"year":1995,"catch":99243},{"year":1996,"catch":112364},{"year":1997,"catch":121860},{"year":1998,"catch":93183},{"year":1999,"catch":70818},{"year":2000,"catch":84866},{"year":2001,"catch":89720},{"year":2002,"catch":87940},{"year":2003,"catch":91864},{"year":2004,"catch":99035},{"year":2005,"catch":101009},{"year":2006,"catch":108258},{"year":2007,"catch":110671},{"year":2008,"catch":115914},{"year":2009,"catch":150215},{"year":2010,"catch":169610},{"year":2011,"catch":199139},{"year":2012,"catch":200272},{"year":2013,"catch":139932},{"year":2014,"catch":127764},{"year":2015,"catch":130087.01},{"year":2016,"catch":145007},{"year":2017,"catch":146616}]
