[{"year":1950,"catch":106900},{"year":1951,"catch":105700},{"year":1952,"catch":118183},{"year":1953,"catch":131157},{"year":1954,"catch":146406},{"year":1955,"catch":152859},{"year":1956,"catch":140480},{"year":1957,"catch":147873},{"year":1958,"catch":137971},{"year":1959,"catch":161603},{"year":1960,"catch":173164},{"year":1961,"catch":185806},{"year":1962,"catch":187341},{"year":1963,"catch":150598},{"year":1964,"catch":136986},{"year":1965,"catch":155978},{"year":1966,"catch":128285},{"year":1967,"catch":119173},{"year":1968,"catch":103737},{"year":1969,"catch":95302},{"year":1970,"catch":114186},{"year":1971,"catch":94783},{"year":1972,"catch":100080},{"year":1973,"catch":96378},{"year":1974,"catch":91155},{"year":1975,"catch":91131},{"year":1976,"catch":135487},{"year":1977,"catch":209190},{"year":1978,"catch":244989},{"year":1979,"catch":141142},{"year":1980,"catch":180879},{"year":1981,"catch":231682},{"year":1982,"catch":237246},{"year":1983,"catch":304558},{"year":1984,"catch":141089},{"year":1985,"catch":81434},{"year":1986,"catch":115022},{"year":1987,"catch":186587},{"year":1988,"catch":118923},{"year":1989,"catch":75130},{"year":1990,"catch":86890},{"year":1991,"catch":75307},{"year":1992,"catch":100142},{"year":1993,"catch":119650},{"year":1994,"catch":106355},{"year":1995,"catch":142800},{"year":1996,"catch":114709},{"year":1997,"catch":132662},{"year":1998,"catch":121775},{"year":1999,"catch":158103},{"year":2000,"catch":144919},{"year":2001,"catch":167895},{"year":2002,"catch":150653},{"year":2003,"catch":134467},{"year":2004,"catch":114018},{"year":2005,"catch":100556},{"year":2006,"catch":109082},{"year":2007,"catch":100824},{"year":2008,"catch":73959},{"year":2009,"catch":72899},{"year":2010,"catch":75992},{"year":2011,"catch":100578},{"year":2012,"catch":97726},{"year":2013,"catch":115941},{"year":2014,"catch":119977},{"year":2015,"catch":126051}]
