[{"year":1950,"catch":693},{"year":1951,"catch":458},{"year":1952,"catch":784},{"year":1953,"catch":961},{"year":1954,"catch":1016},{"year":1955,"catch":1909},{"year":1956,"catch":1957},{"year":1957,"catch":526},{"year":1958,"catch":1214},{"year":1959,"catch":570},{"year":1960,"catch":661},{"year":1961,"catch":3291},{"year":1962,"catch":3617},{"year":1963,"catch":3747},{"year":1964,"catch":12515},{"year":1965,"catch":1440},{"year":1966,"catch":2327},{"year":1967,"catch":5988},{"year":1968,"catch":9962},{"year":1969,"catch":10082},{"year":1970,"catch":3024},{"year":1971,"catch":8911},{"year":1972,"catch":7736},{"year":1973,"catch":2156},{"year":1974,"catch":2555},{"year":1975,"catch":1094},{"year":1976,"catch":6601},{"year":1977,"catch":8331},{"year":1978,"catch":6536},{"year":1979,"catch":3782},{"year":1980,"catch":2200},{"year":1981,"catch":3880},{"year":1982,"catch":6831},{"year":1983,"catch":2662},{"year":1984,"catch":4020},{"year":1985,"catch":3890},{"year":1986,"catch":5401},{"year":1987,"catch":8496},{"year":1988,"catch":13790},{"year":1989,"catch":5935},{"year":1990,"catch":2254},{"year":1991,"catch":2571},{"year":1992,"catch":2613},{"year":1993,"catch":2320},{"year":1994,"catch":3387},{"year":1995,"catch":640},{"year":1996,"catch":6319},{"year":1997,"catch":3634},{"year":1998,"catch":3762},{"year":1999,"catch":1533},{"year":2000,"catch":1109},{"year":2001,"catch":1821},{"year":2002,"catch":2954},{"year":2003,"catch":3973},{"year":2004,"catch":4512},{"year":2005,"catch":2460},{"year":2006,"catch":9342},{"year":2007,"catch":8775},{"year":2008,"catch":5427},{"year":2009,"catch":1282},{"year":2010,"catch":12203},{"year":2011,"catch":4361},{"year":2012,"catch":2602},{"year":2013,"catch":4561},{"year":2014,"catch":5278},{"year":2015,"catch":3673},{"year":2016,"catch":1242},{"year":2017,"catch":2639}]
