[{"year":1950,"catch":600},{"year":1951,"catch":600},{"year":1952,"catch":400},{"year":1953,"catch":600},{"year":1954,"catch":500},{"year":1955,"catch":1000},{"year":1956,"catch":1500},{"year":1957,"catch":1750},{"year":1958,"catch":1750},{"year":1959,"catch":1600},{"year":1960,"catch":2300},{"year":1961,"catch":1600},{"year":1962,"catch":1800},{"year":1963,"catch":1910},{"year":1964,"catch":2320},{"year":1965,"catch":1843},{"year":1966,"catch":1331},{"year":1967,"catch":2071},{"year":1968,"catch":1956},{"year":1969,"catch":1452},{"year":1970,"catch":1482},{"year":1971,"catch":1461},{"year":1972,"catch":2353},{"year":1973,"catch":1582},{"year":1974,"catch":2216},{"year":1975,"catch":3130},{"year":1976,"catch":2353},{"year":1977,"catch":3850},{"year":1978,"catch":4281},{"year":1979,"catch":7252},{"year":1980,"catch":7231},{"year":1981,"catch":6617},{"year":1982,"catch":9394},{"year":1983,"catch":9736},{"year":1984,"catch":9219},{"year":1985,"catch":8112},{"year":1986,"catch":10553},{"year":1987,"catch":10827},{"year":1988,"catch":10707},{"year":1989,"catch":10747},{"year":1990,"catch":13696},{"year":1991,"catch":10232},{"year":1992,"catch":9609},{"year":1993,"catch":6219},{"year":1994,"catch":3600},{"year":1995,"catch":4702},{"year":1996,"catch":5784},{"year":1997,"catch":4574},{"year":1998,"catch":5350},{"year":1999,"catch":6112},{"year":2000,"catch":9500},{"year":2001,"catch":7577},{"year":2002,"catch":7607},{"year":2003,"catch":7263},{"year":2004,"catch":8190},{"year":2005,"catch":9707},{"year":2006,"catch":11167},{"year":2007,"catch":10676},{"year":2008,"catch":21377},{"year":2009,"catch":7897},{"year":2010,"catch":9490},{"year":2011,"catch":15888},{"year":2012,"catch":19687},{"year":2013,"catch":18613},{"year":2014,"catch":16939},{"year":2015,"catch":11622},{"year":2016,"catch":7069},{"year":2017,"catch":13456}]
