[{"year":1950,"catch":873},{"year":1951,"catch":984},{"year":1952,"catch":895},{"year":1953,"catch":892},{"year":1954,"catch":854},{"year":1955,"catch":847},{"year":1956,"catch":838},{"year":1957,"catch":852},{"year":1958,"catch":842},{"year":1959,"catch":857},{"year":1960,"catch":861},{"year":1961,"catch":1136},{"year":1962,"catch":1145},{"year":1963,"catch":1143},{"year":1964,"catch":1947},{"year":1965,"catch":2468},{"year":1966,"catch":2744},{"year":1967,"catch":2286},{"year":1968,"catch":2548},{"year":1969,"catch":2465},{"year":1970,"catch":2930},{"year":1971,"catch":2930},{"year":1972,"catch":2780},{"year":1973,"catch":2380},{"year":1974,"catch":2795},{"year":1975,"catch":10458},{"year":1976,"catch":19399},{"year":1977,"catch":28133},{"year":1978,"catch":23445},{"year":1979,"catch":22101},{"year":1980,"catch":21799},{"year":1981,"catch":17820},{"year":1982,"catch":31769},{"year":1983,"catch":57041},{"year":1984,"catch":50108},{"year":1985,"catch":31697},{"year":1986,"catch":24634},{"year":1987,"catch":35181},{"year":1988,"catch":98353},{"year":1989,"catch":73591},{"year":1990,"catch":75718},{"year":1991,"catch":93258},{"year":1992,"catch":81900},{"year":1993,"catch":91064},{"year":1994,"catch":83055},{"year":1995,"catch":57396},{"year":1996,"catch":56618},{"year":1997,"catch":94794},{"year":1998,"catch":120111},{"year":1999,"catch":60106},{"year":2000,"catch":85538},{"year":2001,"catch":111490},{"year":2002,"catch":153635},{"year":2003,"catch":155888},{"year":2004,"catch":87283},{"year":2005,"catch":79799},{"year":2006,"catch":136251},{"year":2007,"catch":145847},{"year":2008,"catch":112182},{"year":2009,"catch":145004},{"year":2010,"catch":105143},{"year":2011,"catch":65006},{"year":2012,"catch":51926},{"year":2013,"catch":58908},{"year":2014,"catch":80421},{"year":2015,"catch":64962}]
