[{"year":1950,"catch":100},{"year":1951,"catch":100},{"year":1952,"catch":100},{"year":1953,"catch":100},{"year":1954,"catch":100},{"year":1955,"catch":100},{"year":1956,"catch":1850},{"year":1957,"catch":1900},{"year":1958,"catch":3580},{"year":1959,"catch":3700},{"year":1960,"catch":4000},{"year":1961,"catch":4261},{"year":1962,"catch":5050},{"year":1963,"catch":5749},{"year":1964,"catch":7250},{"year":1965,"catch":5705},{"year":1966,"catch":6700},{"year":1967,"catch":6173},{"year":1968,"catch":7075},{"year":1969,"catch":6976},{"year":1970,"catch":15296},{"year":1971,"catch":7308},{"year":1972,"catch":7404},{"year":1973,"catch":11483},{"year":1974,"catch":9500},{"year":1975,"catch":10582},{"year":1976,"catch":9027},{"year":1977,"catch":8717},{"year":1978,"catch":11237},{"year":1979,"catch":10140},{"year":1980,"catch":10133},{"year":1981,"catch":9080},{"year":1982,"catch":10679},{"year":1983,"catch":11060},{"year":1984,"catch":10295},{"year":1985,"catch":98920},{"year":1986,"catch":108854},{"year":1987,"catch":168764},{"year":1988,"catch":156624},{"year":1989,"catch":158463},{"year":1990,"catch":137412},{"year":1991,"catch":154594},{"year":1992,"catch":149012},{"year":1993,"catch":154047},{"year":1994,"catch":134584},{"year":1995,"catch":130530},{"year":1996,"catch":134555},{"year":1997,"catch":221794},{"year":1998,"catch":213001},{"year":1999,"catch":316356},{"year":2000,"catch":283432},{"year":2001,"catch":176609},{"year":2002,"catch":128602},{"year":2003,"catch":142389},{"year":2004,"catch":68867},{"year":2005,"catch":53860},{"year":2006,"catch":143635},{"year":2007,"catch":304062},{"year":2008,"catch":229624},{"year":2009,"catch":73120},{"year":2010,"catch":55192},{"year":2011,"catch":97939},{"year":2012,"catch":102797},{"year":2013,"catch":132668},{"year":2014,"catch":214569},{"year":2015,"catch":269211},{"year":2016,"catch":24243},{"year":2017,"catch":88668}]
