[{"year":1950,"catch":1573},{"year":1951,"catch":1669},{"year":1952,"catch":607},{"year":1953,"catch":621},{"year":1954,"catch":577},{"year":1955,"catch":823},{"year":1956,"catch":803},{"year":1957,"catch":740},{"year":1958,"catch":894},{"year":1959,"catch":790},{"year":1960,"catch":868},{"year":1961,"catch":990},{"year":1962,"catch":984},{"year":1963,"catch":684},{"year":1964,"catch":684},{"year":1965,"catch":1039},{"year":1966,"catch":726},{"year":1967,"catch":512},{"year":1968,"catch":457},{"year":1969,"catch":498},{"year":1970,"catch":500},{"year":1971,"catch":300},{"year":1972,"catch":300},{"year":1973,"catch":400},{"year":1974,"catch":456},{"year":1975,"catch":510},{"year":1976,"catch":404},{"year":1977,"catch":273},{"year":1978,"catch":244},{"year":1979,"catch":440},{"year":1980,"catch":625},{"year":1981,"catch":365},{"year":1982,"catch":429},{"year":1983,"catch":1792},{"year":1984,"catch":1306},{"year":1985,"catch":1150},{"year":1986,"catch":930},{"year":1987,"catch":952},{"year":1988,"catch":1200},{"year":1989,"catch":71},{"year":1990,"catch":86},{"year":1991,"catch":36},{"year":1992,"catch":71},{"year":1993,"catch":38},{"year":1994,"catch":75},{"year":1995,"catch":34},{"year":1996,"catch":65},{"year":1997,"catch":71},{"year":1998,"catch":53},{"year":1999,"catch":41},{"year":2000,"catch":52},{"year":2001,"catch":93},{"year":2002,"catch":424},{"year":2003,"catch":198},{"year":2004,"catch":182},{"year":2005,"catch":148},{"year":2006,"catch":86},{"year":2007,"catch":161},{"year":2008,"catch":143},{"year":2009,"catch":229},{"year":2010,"catch":75},{"year":2011,"catch":93},{"year":2012,"catch":97},{"year":2013,"catch":87},{"year":2014,"catch":85},{"year":2015,"catch":41},{"year":2016,"catch":30},{"year":2017,"catch":32},{"year":2018,"catch":29}]
