[{"year":1950,"catch":1000},{"year":1951,"catch":1000},{"year":1952,"catch":8000},{"year":1953,"catch":10700},{"year":1954,"catch":26300},{"year":1955,"catch":33900},{"year":1956,"catch":23512},{"year":1957,"catch":19920},{"year":1958,"catch":16483},{"year":1959,"catch":16255},{"year":1960,"catch":21308},{"year":1961,"catch":18861},{"year":1962,"catch":16809},{"year":1963,"catch":20865},{"year":1964,"catch":20054},{"year":1965,"catch":19950},{"year":1966,"catch":18777},{"year":1967,"catch":22252},{"year":1968,"catch":24662},{"year":1969,"catch":17410},{"year":1970,"catch":18053},{"year":1971,"catch":20524},{"year":1972,"catch":25616},{"year":1973,"catch":35362},{"year":1974,"catch":51572},{"year":1975,"catch":46030},{"year":1976,"catch":40181},{"year":1977,"catch":47303},{"year":1978,"catch":53827},{"year":1979,"catch":52618},{"year":1980,"catch":53382},{"year":1981,"catch":59576},{"year":1982,"catch":75700},{"year":1983,"catch":86786},{"year":1984,"catch":87467},{"year":1985,"catch":84080},{"year":1986,"catch":74715},{"year":1987,"catch":63081},{"year":1988,"catch":57870},{"year":1989,"catch":53172},{"year":1990,"catch":50895},{"year":1991,"catch":52086},{"year":1992,"catch":47026},{"year":1993,"catch":46928},{"year":1994,"catch":45544},{"year":1995,"catch":14040},{"year":1996,"catch":11165},{"year":1997,"catch":8612},{"year":1998,"catch":7402},{"year":1999,"catch":7043},{"year":2000,"catch":8430},{"year":2001,"catch":7806},{"year":2002,"catch":7940},{"year":2003,"catch":7440},{"year":2004,"catch":6321},{"year":2005,"catch":6102},{"year":2006,"catch":6124},{"year":2007,"catch":7214},{"year":2008,"catch":6011},{"year":2009,"catch":5131},{"year":2010,"catch":5038},{"year":2011,"catch":4889},{"year":2012,"catch":4883},{"year":2013,"catch":5161},{"year":2014,"catch":5363},{"year":2015,"catch":5400}]
