[{"year":1950,"catch":890700},{"year":1951,"catch":1196300},{"year":1952,"catch":1204600},{"year":1953,"catch":949100},{"year":1954,"catch":1462600},{"year":1955,"catch":1135400},{"year":1956,"catch":1376500},{"year":1957,"catch":1010300},{"year":1958,"catch":607700},{"year":1959,"catch":716700},{"year":1960,"catch":689400},{"year":1961,"catch":547000},{"year":1962,"catch":561800},{"year":1963,"catch":513200},{"year":1964,"catch":738700},{"year":1965,"catch":1082100},{"year":1966,"catch":1192500},{"year":1967,"catch":1219000},{"year":1968,"catch":711400},{"year":1969,"catch":192400},{"year":1970,"catch":287600},{"year":1971,"catch":239200},{"year":1972,"catch":158800},{"year":1973,"catch":148900},{"year":1974,"catch":79124},{"year":1975,"catch":43688},{"year":1976,"catch":40860},{"year":1977,"catch":24761},{"year":1978,"catch":23803},{"year":1979,"catch":14274},{"year":1980,"catch":21298},{"year":1981,"catch":26312},{"year":1982,"catch":44299},{"year":1983,"catch":72298},{"year":1984,"catch":162309},{"year":1985,"catch":243919},{"year":1986,"catch":333775},{"year":1987,"catch":348039},{"year":1988,"catch":340478},{"year":1989,"catch":276592},{"year":1990,"catch":207774},{"year":1991,"catch":203090},{"year":1992,"catch":227950},{"year":1993,"catch":352242},{"year":1994,"catch":549623},{"year":1995,"catch":686711},{"year":1996,"catch":763083},{"year":1997,"catch":923175},{"year":1998,"catch":831854},{"year":1999,"catch":829018},{"year":2000,"catch":800069},{"year":2001,"catch":581212},{"year":2002,"catch":573855},{"year":2003,"catch":563165},{"year":2004,"catch":616221},{"year":2005,"catch":748240},{"year":2006,"catch":710613},{"year":2007,"catch":884611},{"year":2008,"catch":1027947},{"year":2009,"catch":1077293},{"year":2010,"catch":923795},{"year":2011,"catch":633123},{"year":2012,"catch":610724},{"year":2013,"catch":507473},{"year":2014,"catch":407306},{"year":2015,"catch":313143}]
